arcade_hubspot_conversations_api/__init__.py
arcade_hubspot_conversations_api/moar/Hubspot_Conversations.json
arcade_hubspot_conversations_api/moar/openapi.json
arcade_hubspot_conversations_api/tools/__init__.py
arcade_hubspot_conversations_api/tools/request_body_schemas.py
arcade_hubspot_conversations_api/wrapper_tools/ArchiveConversationThread.json
arcade_hubspot_conversations_api/wrapper_tools/CreateChannelAccount.json
arcade_hubspot_conversations_api/wrapper_tools/GetChannelAccountDetails.json
arcade_hubspot_conversations_api/wrapper_tools/GetCustomChannelAccounts.json
arcade_hubspot_conversations_api/wrapper_tools/GetCustomChannelMessageDetails.json
arcade_hubspot_conversations_api/wrapper_tools/GetInboxDetails.json
arcade_hubspot_conversations_api/wrapper_tools/GetMessageHistoryForThread.json
arcade_hubspot_conversations_api/wrapper_tools/ListConversationChannels.json
arcade_hubspot_conversations_api/wrapper_tools/ListConversationInboxes.json
arcade_hubspot_conversations_api/wrapper_tools/PublishCustomChannelMessage.json
arcade_hubspot_conversations_api/wrapper_tools/ResolveConversationActors.json
arcade_hubspot_conversations_api/wrapper_tools/RetrieveActorDetails.json
arcade_hubspot_conversations_api/wrapper_tools/RetrieveChannelAccountDetails.json
arcade_hubspot_conversations_api/wrapper_tools/RetrieveChannelAccounts.json
arcade_hubspot_conversations_api/wrapper_tools/RetrieveChannelDetails.json
arcade_hubspot_conversations_api/wrapper_tools/RetrieveConversationThreads.json
arcade_hubspot_conversations_api/wrapper_tools/RetrieveFullMessageContent.json
arcade_hubspot_conversations_api/wrapper_tools/RetrieveThreadById.json
arcade_hubspot_conversations_api/wrapper_tools/RetrieveThreadMessage.json
arcade_hubspot_conversations_api/wrapper_tools/SendConversationMessage.json
arcade_hubspot_conversations_api/wrapper_tools/UpdateChannelAccountInfo.json
arcade_hubspot_conversations_api/wrapper_tools/UpdateChannelAccountStaging.json
arcade_hubspot_conversations_api-1.0.0.dist-info/METADATA
arcade_hubspot_conversations_api-1.0.0.dist-info/WHEEL
arcade_hubspot_conversations_api-1.0.0.dist-info/entry_points.txt
arcade_hubspot_conversations_api-1.0.0.dist-info/licenses/LICENSE
arcade_hubspot_conversations_api-1.0.0.dist-info/RECORD
